{
  "admin_users": {
    "admin": {
      "password_hash": "180eebfcf6bec0aed4577215105319b8:a8e5d22dce8596f141aa70df81940528c996b3cebbb5dae4147560d57922594c",
      "name": "Administrador",
      "email": "admin@universidad.edu.mx",
      "created_at": "2025-10-15T11:56:01.733600",
      "active": true
    }
  },
  "session_settings": {
    "timeout_hours": 8,
    "require_https": false,
    "max_failed_attempts": 5,
    "lockout_duration_minutes": 30
  },
  "security_settings": {
    "password_min_length": 8,
    "require_special_chars": true,
    "session_secret": "120577c341d6e1bdff0b8e7c7249ec93dbaacdd8aa2b52a42d677e6edff1ad29"
  }
}